apidoc2markdown/apidoc.md.j2
apidoc2markdown/apidoc2markdown.py
apidoc2markdown-0.1.0.dist-info/DESCRIPTION.rst
apidoc2markdown-0.1.0.dist-info/METADATA
apidoc2markdown-0.1.0.dist-info/RECORD
apidoc2markdown-0.1.0.dist-info/WHEEL
apidoc2markdown-0.1.0.dist-info/entry_points.txt
apidoc2markdown-0.1.0.dist-info/metadata.json
apidoc2markdown-0.1.0.dist-info/top_level.txt
