Metadata-Version: 2.0
Name: apidoc2markdown
Version: 0.1.0
Summary: Converter from Apidoc JSON to Markdown.
Home-page: https://github.com/moigagoo/apidoc2markdown
Author: Konstantin Molchanov
Author-email: moigagoo@live.com
License: MIT
Download-URL: https://pypi.org/project/apidoc2markdown
Platform: any
Classifier: Development Status :: 4 - Beta
Classifier: Environment :: Console
Classifier: Environment :: Web Environment
Classifier: Intended Audience :: Developers
Classifier: License :: OSI Approved :: MIT License
Classifier: Operating System :: OS Independent
Classifier: Programming Language :: Python
Classifier: Topic :: Documentation
Classifier: Topic :: Utilities
Requires-Dist: Jinja2
